gitstorage/__init__.py
gitstorage/__version__.py
gitstorage-23.4.10.1.dist-info/METADATA
gitstorage-23.4.10.1.dist-info/WHEEL
gitstorage-23.4.10.1.dist-info/top_level.txt
gitstorage-23.4.10.1.dist-info/RECORD
